<title>
    O TRÁFICO NEGREIRO
</title>
<image src="images/historia_2008_m_21_0.png" />
<source>
    Mapa baseado no original: PÉTRÉ-GRENOVILLEAN, Olivier. La documentation
    photographique. In: <b>Les traites negrières</b>. Paris: 2003. p. 29.
</source>
<image src="images/historia_2008_m_21_1.png" />
<question>
    Na análise do mapa e do gráfico sobre o ritmo do
    tráfico negreiro, conclui-se que,
</question>
<answer_options>
    <item>
        no século XIX, houve uma diminuição do fluxo
        de escravos africanos para Cuba.
    </item>
    <item>
        no século XIX, a proibição do tráfico negreiro
        nas colônias britânicas eliminou o fluxo de
        escravos para a América do Norte.
    </item>
    <item>
        nos séculos XVIII e XIX, o fluxo de escravos
        africanos para regiões de colonização portuguesa
        na América sofreu pouca oscilação.
    </item>
    <item>
        ao longo do século XVII, a maioria dos
        escravos africanos transportados para a
        América dirigiu-se para colônias espanholas.
    </item>
    <item>
        no último quartel do século XVII, houve um
        aumento do fluxo de escravos africanos para
        a América Espanhola Continental.
    </item>
</answer_options>
